webtoon_data.py
webtoon_data-0.1.1.dist-info/LICENSE
webtoon_data-0.1.1.dist-info/METADATA
webtoon_data-0.1.1.dist-info/WHEEL
webtoon_data-0.1.1.dist-info/RECORD
