Metadata-Version: 2.1
Name: webtoon-data
Version: 0.1.1
Summary: Python wrapper for Webtoon data
Home-page: https://github.com/ekimz/webtoon_data
License: MIT
Author: Kim Eunji
Requires-Python: >=3.9,<4.0
Classifier: License :: OSI Approved :: MIT License
Classifier: Programming Language :: Python :: 3
Classifier: Programming Language :: Python :: 3.9
Classifier: Programming Language :: Python :: 3.10
Classifier: Programming Language :: Python :: 3.11
Project-URL: Documentation, https://webtoon-data.readthedocs.io/en/latest/
Project-URL: Repository, https://github.com/ekimz/webtoon_data
